labothappy/__init__.py
labothappy/component/__init__.py
labothappy/component/base_component.py
labothappy/component/template.py
labothappy/component/heat_exchanger/__init__.py
labothappy/component/heat_exchanger/sizing/__init__.py
labothappy/component/heat_exchanger/sizing/basic_sizing.py
labothappy/component/heat_exchanger/sizing/heat_pipe_HTX/__init__.py
labothappy/component/heat_exchanger/sizing/heat_pipe_HTX/post_process.py
labothappy/component/heat_exchanger/sizing/heat_pipe_HTX/sizing_HP_HTX.py
labothappy/component/heat_exchanger/sizing/heat_pipe_HTX/modules/Airflow.py
labothappy/component/heat_exchanger/sizing/heat_pipe_HTX/modules/HP_h_coeffs.py
labothappy/component/heat_exchanger/sizing/heat_pipe_HTX/modules/HP_internal.py
labothappy/component/heat_exchanger/sizing/heat_pipe_HTX/modules/HP_tube_model.py
labothappy/component/heat_exchanger/sizing/heat_pipe_HTX/modules/P_max_steel_pipes.py
labothappy/component/heat_exchanger/sizing/heat_pipe_HTX/modules/__init__.py
labothappy/component/heat_exchanger/steady_state/__init__.py
labothappy/component/heat_exchanger/steady_state/cst_efficiency/__init__.py
labothappy/component/heat_exchanger/steady_state/cst_efficiency/example.py
labothappy/component/heat_exchanger/steady_state/cst_efficiency/simulation_model.py
labothappy/component/heat_exchanger/steady_state/epsilon_NTU/__init__.py
labothappy/component/heat_exchanger/steady_state/epsilon_NTU/example.py
labothappy/component/heat_exchanger/steady_state/epsilon_NTU/simulation_model.py
labothappy/component/heat_exchanger/steady_state/epsilon_NTU/modules/__init__.py
labothappy/component/heat_exchanger/steady_state/epsilon_NTU/modules/pipe_HTC.py
labothappy/component/heat_exchanger/steady_state/finite_volumes/__init__.py
labothappy/component/heat_exchanger/steady_state/finite_volumes/cross_flow_tube_and_fins/__init__.py
labothappy/component/heat_exchanger/steady_state/finite_volumes/cross_flow_tube_and_fins/example_main.py
LaboThapPy-0.1.0.dist-info/LICENSE
LaboThapPy-0.1.0.dist-info/METADATA
LaboThapPy-0.1.0.dist-info/WHEEL
LaboThapPy-0.1.0.dist-info/top_level.txt
LaboThapPy-0.1.0.dist-info/RECORD
