Metadata-Version: 2.1
Name: LaboThapPy
Version: 0.1.0
Summary: Open-source Python library for the modelling and simulation of thermodynamic systems
Home-page: https://github.com/PyLaboThap/LaboThapPy
Author: Elise Neven, Basile Chaudoir
Requires-Python: >=3.6
License-File: LICENSE
